{
    "clients": {
        "Geth": {
            "version": "1.6.2",
            "platforms": {
                "linux": {
                    "x64": {
                        "download": {
                            "url": "https://gethstore.blob.core.windows.net/builds/geth-linux-amd64-1.6.2-65979770.tar.gz",
                            "type": "tar",
                            "md5": "994da87ac8e4ff16b3c35750068ddee6",
                            "bin": "geth-linux-amd64-1.6.2-65979770/geth"
                        },
                        "bin": "geth",
                        "commands": {
                            "sanity": {
                                "args": [
                                    "version"
                                ],
                                "output": [
                                    "Geth",
                                    "1.6.2"
                                ]
                            }
                        }
                    },
                    "ia32": {
                        "download": {
                            "url": "https://gethstore.blob.core.windows.net/builds/geth-linux-386-1.6.2-65979770.tar.gz",
                            "type": "tar",
                            "md5": "d1f6ef647c1961038965b11023ef73db",
                            "bin": "geth-linux-386-1.6.2-65979770/geth"
                        },
                        "bin": "geth",
                        "commands": {
                            "sanity": {
                                "args": [
                                    "version"
                                ],
                                "output": [
                                    "Geth",
                                    "1.6.2"
                                ]
                            }
                        }
                    }
                },
                "mac": {
                    "x64": {
                        "download": {
                            "url": "https://gethstore.blob.core.windows.net/builds/geth-darwin-amd64-1.6.2-65979770.tar.gz",
                            "type": "tar",
                            "md5": "5c1923fd1ef22d3ef4e73d46557c38d6",
                            "bin": "geth-darwin-amd64-1.6.2-65979770/geth"
                        },
                        "bin": "geth",
                        "commands": {
                            "sanity": {
                                "args": [
                                    "version"
                                ],
                                "output": [
                                    "Geth",
                                    "1.6.2"
                                ]
                            }
                        }
                    }
                },
                "win": {
                    "x64": {
                        "download": {
                            "url": "https://gethstore.blob.core.windows.net/builds/geth-windows-amd64-1.6.2-65979770.zip",
                            "type": "zip",
                            "md5": "d3f4c14f69714fea407a6b81ec45d1b9",
                            "bin": "geth-windows-amd64-1.6.2-65979770\\geth.exe"
                        },
                        "bin": "geth.exe",
                        "commands": {
                            "sanity": {
                                "args": [
                                    "version"
                                ],
                                "output": [
                                    "Geth",
                                    "1.6.2"
                                ]
                            }
                        }
                    },
                    "ia32": {
                        "download": {
                            "url": "https://gethstore.blob.core.windows.net/builds/geth-windows-386-1.6.2-65979770.zip",
                            "type": "zip",
                            "md5": "fad7ee50051ae38d03c318131053974c",
                            "bin": "geth-windows-386-1.6.2-65979770\\geth.exe"
                        },
                        "bin": "geth.exe",
                        "commands": {
                            "sanity": {
                                "args": [
                                    "version"
                                ],
                                "output": [
                                    "Geth",
                                    "1.6.2"
                                ]
                            }
                        }
                    }
                }
            }
        }
    }
}